openstack_debugger/__init__.py
openstack_debugger/debugger.py
openstack_debugger/version.py
openstack_debugger/conf/__init__.py
openstack_debugger/conf/remote_debug.py
openstack.debugger-1.0.3.dist-info/AUTHORS
openstack.debugger-1.0.3.dist-info/METADATA
openstack.debugger-1.0.3.dist-info/WHEEL
openstack.debugger-1.0.3.dist-info/pbr.json
openstack.debugger-1.0.3.dist-info/top_level.txt
openstack.debugger-1.0.3.dist-info/RECORD
