Metadata-Version: 2.1
Name: openstack.debugger
Version: 1.0.3
Summary: OpenStack Configuration for Debugging
Home-page: https://gitlabix.gabia.io/cloud/openstack/
Author: nobody
Author-email: cloud_dev@gabia.com
Classifier: Development Status :: 4 - Beta
Classifier: Environment :: OpenStack
Classifier: Intended Audience :: Developers
Classifier: License :: OSI Approved :: Apache Software License
Classifier: Operating System :: OS Independent
Classifier: Programming Language :: Python
Classifier: Programming Language :: Python :: 3
Classifier: Programming Language :: Python :: 3.8
Classifier: Programming Language :: Python :: 3.9
Classifier: Programming Language :: Python :: 3.10
Classifier: Programming Language :: Python :: 3.11
Classifier: Programming Language :: Python :: 3 :: Only
Requires-Python: >=3.8
License-File: AUTHORS
Requires-Dist: pbr !=2.1.0,>=2.0.0
Requires-Dist: tox <5.0.0,>=3.18.0
Requires-Dist: oslo.config >=6.8.0
Requires-Dist: oslo.log >=3.44.0
Requires-Dist: debugpy >=1.8.2
